ffmpeg_mcp/__init__.py
ffmpeg_mcp/bin/.gitkeep
ffmpeg_mcp/cut_video.py
ffmpeg_mcp/ffmpeg.py
ffmpeg_mcp/server.py
ffmpeg_mcp/typedef.py
ffmpeg_mcp/utils.py
mseep_ffmpeg_mcp-1.0.1.dist-info/LICENSE
mseep_ffmpeg_mcp-1.0.1.dist-info/METADATA
mseep_ffmpeg_mcp-1.0.1.dist-info/WHEEL
mseep_ffmpeg_mcp-1.0.1.dist-info/entry_points.txt
mseep_ffmpeg_mcp-1.0.1.dist-info/RECORD
